chatora/util/__init__.py
chatora/util/_pkg_info.py
chatora/util/constant.py
chatora/util/functional.py
chatora/util/import_symbol.py
chatora/util/marker.py
chatora/util/os_signal.py
chatora.util-0.2.5.dist-info/LICENSE.txt
chatora.util-0.2.5.dist-info/METADATA
chatora.util-0.2.5.dist-info/WHEEL
chatora.util-0.2.5.dist-info/top_level.txt
chatora.util-0.2.5.dist-info/zip-safe
chatora.util-0.2.5.dist-info/RECORD
