Metadata-Version: 2.1
Name: chatora.util
Version: 0.2.5
Summary: Helper utilities for python.
Home-page: https://github.com/takaomag/chatora.util
Author: Takao Magoori
Author-email: takaomag@users.noreply.github.com
Maintainer: Takao Magoori
Maintainer-email: takaomag@users.noreply.github.com
License: MIT
Download-URL: https://github.com/takaomag/chatora.util/releases
Project-URL: source code, https://github.com/takaomag/chatora.util
Project-URL: issues, https://github.com/takaomag/chatora.util/issues
Project-URL: documentation, https://github.com/takaomag/chatora.util/blob/master/README.md
Keywords: util
Platform: UNKNOWN
Classifier: Development Status :: 4 - Beta
Classifier: Environment :: Other Environment
Classifier: Intended Audience :: Developers
Classifier: License :: OSI Approved :: MIT License
Classifier: Natural Language :: English
Classifier: Operating System :: POSIX :: Linux
Classifier: Programming Language :: Python :: 3 :: Only
Classifier: Programming Language :: Python :: 3.7
Classifier: Programming Language :: Python :: Implementation :: CPython
Classifier: Topic :: Software Development :: Libraries :: Python Modules
Requires-Python: >=3.7
Requires-Dist: setuptools (>=41.0.1)
Requires-Dist: pip (>=19.1.1)
Requires-Dist: wheel (>=0.33.1)
Requires-Dist: packaging (>=19.0)
Provides-Extra: dev
Requires-Dist: bumpversion (>=0.5.3) ; extra == 'dev'
Requires-Dist: check-manifest (>=0.38) ; extra == 'dev'
Requires-Dist: colorama (>=0.4.1) ; extra == 'dev'
